.coveragerc
.gitignore
.gitmodules
.readthedocs.yml
CHANGELOG.md
LICENSE
MANIFEST.in
README.md
pyproject.toml
setup.cfg
setup.py
.ci/install-deps.sh
.ci/run.sh
.github/codeql.yml
.github/dependabot.yml
.github/workflows/codeql.yml
.github/workflows/publish_pkg.yaml
.github/workflows/tests.yaml
docs/CODE_OF_CONDUCT.md
docs/SECURITY.md
docs/api.rst
docs/conf.py
docs/constants.rst
docs/contributing.rst
docs/esys.rst
docs/exception.rst
docs/fapi.rst
docs/index.rst
docs/install.rst
docs/maintainers.rst
docs/policy.rst
docs/project.rst
docs/release.rst
docs/requirements.txt
docs/sphinx-finished.sh
docs/tcti.rst
docs/testing.rst
docs/tsskey.rst
docs/types.rst
docs/utils.rst
docs/_static/.gitkeep
scripts/docs.sh
scripts/get_deps.py
scripts/libtss2_build.py
scripts/prepare_headers.py
src/tpm2_pytss/ESAPI.py
src/tpm2_pytss/FAPI.py
src/tpm2_pytss/TCTI.py
src/tpm2_pytss/TCTILdr.py
src/tpm2_pytss/TCTISPIHelper.py
src/tpm2_pytss/TSS2_Exception.py
src/tpm2_pytss/__init__.py
src/tpm2_pytss/constants.py
src/tpm2_pytss/encoding.py
src/tpm2_pytss/fapi_info.py
src/tpm2_pytss/policy.py
src/tpm2_pytss/tsskey.py
src/tpm2_pytss/types.py
src/tpm2_pytss/utils.py
src/tpm2_pytss.egg-info/PKG-INFO
src/tpm2_pytss.egg-info/SOURCES.txt
src/tpm2_pytss.egg-info/dependency_links.txt
src/tpm2_pytss.egg-info/requires.txt
src/tpm2_pytss.egg-info/top_level.txt
src/tpm2_pytss/internal/__init__.py
src/tpm2_pytss/internal/crypto.py
src/tpm2_pytss/internal/templates.py
src/tpm2_pytss/internal/utils.py
test/TSS2_BaseTest.py
test/__init__.py
test/test_crypto.py
test/test_encoding.py
test/test_esapi.py
test/test_exception.py
test/test_fapi.py
test/test_import.py
test/test_internal.py
test/test_policy.py
test/test_tcti.py
test/test_tcti_spi_helper.py
test/test_tsskey.py
test/test_types.py
test/test_utils.py