Metadata-Version: 2.1
Name: tpm2-pytss
Version: 2.2.1
Summary: TPM 2.0 TSS Bindings for Python
Home-page: https://github.com/tpm2-software/tpm2-pytss
Author: William Roberts
Author-email: william.c.roberts@intel.com
License: BSD
Platform: UNKNOWN
Classifier: Intended Audience :: Developers
Classifier: License :: OSI Approved :: BSD License
Classifier: Natural Language :: English
Classifier: Operating System :: OS Independent
Classifier: Programming Language :: Python :: 3.8
Classifier: Programming Language :: Python :: 3.9
Classifier: Programming Language :: Python :: 3.10
Classifier: Programming Language :: Python :: 3.11
Classifier: Programming Language :: Python :: 3.12
Provides-Extra: dev
